cryptodatahub/__init__.py
cryptodatahub/__setup__.py
cryptodatahub/common/__init__.py
cryptodatahub/common/algorithm.py
cryptodatahub/common/attack-named.json
cryptodatahub/common/attack-type.json
cryptodatahub/common/authentication.json
cryptodatahub/common/block-cipher-mode.json
cryptodatahub/common/block-cipher.json
cryptodatahub/common/certificate-transparency-log.json
cryptodatahub/common/client.json
cryptodatahub/common/dhparam-well-known.json
cryptodatahub/common/ecparam-well-known.json
cryptodatahub/common/entity.json
cryptodatahub/common/entity.py
cryptodatahub/common/exception.py
cryptodatahub/common/fetcher.py
cryptodatahub/common/grade.py
cryptodatahub/common/hash.json
cryptodatahub/common/key-exchange.json
cryptodatahub/common/key.py
cryptodatahub/common/mac.json
cryptodatahub/common/named-group.json
cryptodatahub/common/parameter.py
cryptodatahub/common/root-certificate.json
cryptodatahub/common/server.json
cryptodatahub/common/signature.json
cryptodatahub/common/standard.json
cryptodatahub/common/stores.py
cryptodatahub/common/types.py
cryptodatahub/common/utils.py
cryptodatahub/common/vulnerability.json
cryptodatahub/dnsrec/__init__.py
cryptodatahub/dnsrec/algorithm.json
cryptodatahub/dnsrec/algorithm.py
cryptodatahub/dnsrec/digest-type.json
cryptodatahub/dnsrec/rr-type.json
cryptodatahub/ssh/__init__.py
cryptodatahub/ssh/algorithm.py
cryptodatahub/ssh/compression-algorithm.json
cryptodatahub/ssh/elliptic-curve-identifier.json
cryptodatahub/ssh/encryption-algorithm.json
cryptodatahub/ssh/host-key-algorithm.json
cryptodatahub/ssh/kex-algorithm.json
cryptodatahub/ssh/mac-algorithm.json
cryptodatahub/tls/__init__.py
cryptodatahub/tls/algorithm.py
cryptodatahub/tls/certificate-compression-algorithm.json
cryptodatahub/tls/cipher-kind.json
cryptodatahub/tls/cipher-suite-extension.json
cryptodatahub/tls/cipher-suite.json
cryptodatahub/tls/client.json
cryptodatahub/tls/client.py
cryptodatahub/tls/compression-method.json
cryptodatahub-1.0.2.dist-info/licenses/LICENSE.txt
cryptodatahub-1.0.2.dist-info/METADATA
cryptodatahub-1.0.2.dist-info/WHEEL
cryptodatahub-1.0.2.dist-info/entry_points.txt
cryptodatahub-1.0.2.dist-info/top_level.txt
cryptodatahub-1.0.2.dist-info/RECORD
