Metadata-Version: 2.4
Name: CryptoDataHub
Version: 1.0.2
Summary: Repository of cryptography-related data
Author-email: Szilárd Pfeiffer <coroner@pfeifferszilard.hu>
Maintainer-email: Szilárd Pfeiffer <coroner@pfeifferszilard.hu>
License: MPL-2.0
Project-URL: Homepage, https://gitlab.com/coroner/cryptodatahub
Project-URL: Changelog, https://cryptodatahub.readthedocs.io/en/latest/changelog
Project-URL: Documentation, https://cryptodatahub.readthedocs.io/en/latest/
Project-URL: Issues, https://gitlab.com/coroner/cryptodatahub/-/issues
Project-URL: Source, https://gitlab.com/coroner/cryptodatahub
Keywords: ssl,tls,ssh,dns,dnssec
Classifier: Development Status :: 5 - Production/Stable
Classifier: Environment :: Console
Classifier: Framework :: tox
Classifier: Intended Audience :: Information Technology
Classifier: Intended Audience :: Science/Research
Classifier: Intended Audience :: System Administrators
Classifier: Natural Language :: English
Classifier: Operating System :: MacOS
Classifier: Operating System :: Microsoft :: Windows
Classifier: Operating System :: POSIX
Classifier: Programming Language :: Python :: 3.9
Classifier: Programming Language :: Python :: 3.10
Classifier: Programming Language :: Python :: 3.11
Classifier: Programming Language :: Python :: 3.12
Classifier: Programming Language :: Python :: 3.13
Classifier: Programming Language :: Python :: 3.14
Classifier: Programming Language :: Python :: Implementation :: CPython
Classifier: Programming Language :: Python :: Implementation :: PyPy
Classifier: Programming Language :: Python
Classifier: Topic :: Internet
Classifier: Topic :: Security
Classifier: Topic :: Security :: Cryptography
Classifier: Topic :: Software Development :: Libraries :: Python Modules
License-File: LICENSE.txt
Requires-Dist: asn1crypto
Requires-Dist: attrs
Requires-Dist: python-dateutil
Requires-Dist: urllib3
Provides-Extra: tests
Requires-Dist: pyfakefs; extra == "tests"
Requires-Dist: beautifulsoup4; extra == "tests"
Provides-Extra: docs
Requires-Dist: sphinx; extra == "docs"
Requires-Dist: sphinx-sitemap; extra == "docs"
Dynamic: license-file
